{"cameraMode":{"drawMode":0,"name":"Shaded","section":"Shading Mode"},"sceneLighting":true,"audioPlay":false,"sceneViewState":{"showFog":true,"showMaterialUpdate":false,"showSkybox":true,"showFlares":true,"showImageEffects":true,"showParticleSystems":true},"in2DMode":false,"pivot":{"x":0.8956131339073181,"y":0.31601208448410036,"z":-2.8929834365844728},"rotation":{"x":-0.04516664892435074,"y":0.3535328507423401,"z":-0.017087802290916444,"w":-0.9341945052146912},"size":0.6980495452880859,"orthographic":false}